devenv_genie-0.2.4.dist-info/licenses/LICENSE
devenv_genie_pkg/__init__.py
devenv_genie_pkg/cli.py
devenv_genie_pkg/tools_config.json
devenv_genie-0.2.4.dist-info/METADATA
devenv_genie-0.2.4.dist-info/WHEEL
devenv_genie-0.2.4.dist-info/entry_points.txt
devenv_genie-0.2.4.dist-info/top_level.txt
devenv_genie-0.2.4.dist-info/RECORD
