Metadata-Version: 2.4
Name: devenv-genie
Version: 0.2.4
Summary: AI-Powered Dev Environment Diagnoser & Fixer. Helps set up and troubleshoot local dev environments.
Author-email: Hamdaan Baloch <hamdaanbaloch6@gmail.com>
License: MIT License
Project-URL: Homepage, https://github.com/yourusername/devenv-genie
Project-URL: Bug Tracker, https://github.com/yourusername/devenv-genie/issues
Keywords: developer tools,devops,ai,environment setup,cli,diagnostics
Classifier: Development Status :: 4 - Beta
Classifier: Programming Language :: Python :: 3
Classifier: Programming Language :: Python :: 3.9
Classifier: Programming Language :: Python :: 3.10
Classifier: Programming Language :: Python :: 3.11
Classifier: Programming Language :: Python :: 3.12
Classifier: License :: OSI Approved :: MIT License
Classifier: Operating System :: OS Independent
Classifier: Environment :: Console
Classifier: Intended Audience :: Developers
Classifier: Topic :: Software Development :: Build Tools
Classifier: Topic :: Utilities
Requires-Python: >=3.9
License-File: LICENSE
Requires-Dist: groq>=0.9.0
Requires-Dist: python-dotenv>=0.20.0
Requires-Dist: click>=8.0.0
Requires-Dist: packaging>=21.0
Requires-Dist: appdirs>=1.4.0
Dynamic: license-file
